[{"Date": "09/01/2007 11:16:18 AM", "Beat": "1731", "Primary Type": "ARSON", "ID": "5754399"},{"Date": "09/02/2007 01:40:37 AM", "Beat": "1433", "Primary Type": "ARSON", "ID": "5754669"},{"Date": "09/01/2007 02:16:15 AM", "Beat": "1513", "Primary Type": "ARSON", "ID": "5754796"},{"Date": "09/02/2007 09:51:54 AM", "Beat": "2534", "Primary Type": "ARSON", "ID": "5755586"},{"Date": "09/03/2007 01:29:28 AM", "Beat": "2521", "Primary Type": "ARSON", "ID": "5755809"},{"Date": "09/02/2007 11:09:25 PM", "Beat": "2521", "Primary Type": "ARSON", "ID": "5755827"},{"Date": "09/02/2007 05:11:00 AM", "Beat": "0822", "Primary Type": "ARSON", "ID": "5756277"},{"Date": "09/03/2007 04:38:26 AM", "Beat": "1132", "Primary Type": "ARSON", "ID": "5756477"},{"Date": "09/03/2007 09:10:00 PM", "Beat": "2514", "Primary Type": "ARSON", "ID": "5757292"},{"Date": "09/02/2007 08:00:00 AM", "Beat": "2232", "Primary Type": "ARSON", "ID": "5760481"},{"Date": "09/07/2007 03:25:00 AM", "Beat": "1222", "Primary Type": "ARSON", "ID": "5763868"},{"Date": "09/07/2007 02:53:37 AM", "Beat": "0712", "Primary Type": "ARSON", "ID": "5766664"},{"Date": "09/10/2007 05:17:00 AM", "Beat": "0931", "Primary Type": "ARSON", "ID": "5769518"},{"Date": "09/11/2007 03:09:38 AM", "Beat": "2222", "Primary Type": "ARSON", "ID": "5772141"},{"Date": "09/10/2007 12:14:36 PM", "Beat": "0915", "Primary Type": "ARSON", "ID": "5773130"},{"Date": "09/12/2007 10:20:00 PM", "Beat": "2411", "Primary Type": "ARSON", "ID": "5775904"},{"Date": "09/14/2007 04:50:00 AM", "Beat": "0715", "Primary Type": "ARSON", "ID": "5778323"},{"Date": "09/14/2007 03:45:00 AM", "Beat": "0511", "Primary Type": "ARSON", "ID": "5779286"},{"Date": "09/14/2007 02:36:32 PM", "Beat": "0414", "Primary Type": "ARSON", "ID": "5779591"},{"Date": "09/15/2007 05:50:00 AM", "Beat": "1034", "Primary Type": "ARSON", "ID": "5780672"},{"Date": "09/15/2007 11:30:00 PM", "Beat": "0832", "Primary Type": "ARSON", "ID": "5780676"},{"Date": "09/16/2007 04:45:00 AM", "Beat": "2234", "Primary Type": "ARSON", "ID": "5781235"},{"Date": "09/15/2007 09:30:13 PM", "Beat": "0825", "Primary Type": "ARSON", "ID": "5781345"},{"Date": "09/16/2007 03:53:00 AM", "Beat": "1431", "Primary Type": "ARSON", "ID": "5781831"},{"Date": "09/17/2007 02:10:00 AM", "Beat": "0532", "Primary Type": "ARSON", "ID": "5781970"},{"Date": "09/16/2007 05:26:00 AM", "Beat": "1622", "Primary Type": "ARSON", "ID": "5782106"},{"Date": "09/16/2007 10:08:03 PM", "Beat": "0821", "Primary Type": "ARSON", "ID": "5782772"},{"Date": "09/15/2007 04:00:00 PM", "Beat": "1824", "Primary Type": "ARSON", "ID": "5782868"},{"Date": "09/17/2007 10:10:17 PM", "Beat": "0821", "Primary Type": "ARSON", "ID": "5784027"},{"Date": "09/18/2007 12:25:00 AM", "Beat": "2212", "Primary Type": "ARSON", "ID": "5784738"},{"Date": "09/18/2007 08:10:33 PM", "Beat": "0232", "Primary Type": "ARSON", "ID": "5786335"},{"Date": "09/17/2007 10:30:00 PM", "Beat": "2524", "Primary Type": "ARSON", "ID": "5786555"},{"Date": "09/19/2007 07:51:18 AM", "Beat": "0532", "Primary Type": "ARSON", "ID": "5787882"},{"Date": "09/19/2007 03:17:48 AM", "Beat": "2411", "Primary Type": "ARSON", "ID": "5787967"},{"Date": "09/19/2007 11:30:00 PM", "Beat": "0913", "Primary Type": "ARSON", "ID": "5788648"},{"Date": "09/20/2007 11:29:00 AM", "Beat": "2234", "Primary Type": "ARSON", "ID": "5791123"},{"Date": "09/19/2007 07:49:14 PM", "Beat": "0723", "Primary Type": "ARSON", "ID": "5791473"},{"Date": "09/20/2007 08:43:26 PM", "Beat": "0712", "Primary Type": "ARSON", "ID": "5791784"},{"Date": "09/20/2007 07:05:00 AM", "Beat": "0725", "Primary Type": "ARSON", "ID": "5791870"},{"Date": "09/22/2007 06:47:08 AM", "Beat": "1531", "Primary Type": "ARSON", "ID": "5794686"},{"Date": "09/22/2007 06:35:00 PM", "Beat": "0423", "Primary Type": "ARSON", "ID": "5795526"},{"Date": "09/22/2007 10:00:00 AM", "Beat": "0321", "Primary Type": "ARSON", "ID": "5795696"},{"Date": "09/24/2007 11:15:00 PM", "Beat": "1531", "Primary Type": "ARSON", "ID": "5797984"},{"Date": "09/25/2007 03:56:59 AM", "Beat": "0414", "Primary Type": "ARSON", "ID": "5798441"},{"Date": "09/25/2007 12:35:00 AM", "Beat": "1032", "Primary Type": "ARSON", "ID": "5799418"},{"Date": "09/25/2007 11:22:55 PM", "Beat": "1121", "Primary Type": "ARSON", "ID": "5800331"},{"Date": "09/25/2007 01:45:13 PM", "Beat": "1111", "Primary Type": "ARSON", "ID": "5801016"},{"Date": "09/25/2007 05:00:00 AM", "Beat": "0631", "Primary Type": "ARSON", "ID": "5801605"},{"Date": "09/27/2007 01:34:34 AM", "Beat": "1113", "Primary Type": "ARSON", "ID": "5802649"},{"Date": "09/26/2007 11:49:27 PM", "Beat": "0713", "Primary Type": "ARSON", "ID": "5804918"},{"Date": "09/28/2007 02:00:00 AM", "Beat": "1624", "Primary Type": "ARSON", "ID": "5805572"},{"Date": "09/28/2007 12:51:01 AM", "Beat": "1624", "Primary Type": "ARSON", "ID": "5807184"},{"Date": "09/28/2007 12:45:00 PM", "Beat": "1331", "Primary Type": "ARSON", "ID": "5807746"},{"Date": "09/29/2007 06:30:00 AM", "Beat": "0832", "Primary Type": "ARSON", "ID": "5807899"},{"Date": "09/30/2007 12:24:07 AM", "Beat": "0714", "Primary Type": "ARSON", "ID": "5808573"},{"Date": "09/30/2007 04:08:00 AM", "Beat": "0532", "Primary Type": "ARSON", "ID": "5809268"},{"Date": "09/30/2007 11:40:54 PM", "Beat": "1532", "Primary Type": "ARSON", "ID": "5809723"},{"Date": "09/29/2007 07:38:00 PM", "Beat": "1424", "Primary Type": "ARSON", "ID": "5810647"},{"Date": "09/30/2007 05:55:00 PM", "Beat": "2123", "Primary Type": "ARSON", "ID": "5810883"},{"Date": "09/30/2007 11:20:34 PM", "Beat": "0813", "Primary Type": "ARSON", "ID": "5811719"}]