[{"Date": "09/26/2008 02:30:00 PM", "Beat": "0813", "Primary Type": "STALKING", "ID": "6538275"},{"Date": "09/01/2008 09:15:00 PM", "Beat": "1322", "Primary Type": "STALKING", "ID": "6468801"},{"Date": "09/04/2008 05:00:00 PM", "Beat": "2333", "Primary Type": "STALKING", "ID": "6480186"},{"Date": "09/06/2008 05:45:00 AM", "Beat": "0614", "Primary Type": "STALKING", "ID": "6482509"},{"Date": "09/03/2008 02:30:00 PM", "Beat": "0512", "Primary Type": "STALKING", "ID": "6484728"},{"Date": "09/02/2008 09:00:00 PM", "Beat": "0832", "Primary Type": "STALKING", "ID": "6491094"},{"Date": "09/10/2008 08:10:00 PM", "Beat": "1122", "Primary Type": "STALKING", "ID": "6491524"},{"Date": "09/05/2008 02:00:00 PM", "Beat": "0735", "Primary Type": "STALKING", "ID": "6499530"},{"Date": "09/18/2008 08:45:00 AM", "Beat": "1134", "Primary Type": "STALKING", "ID": "6505019"},{"Date": "09/20/2008 09:12:44 AM", "Beat": "1922", "Primary Type": "STALKING", "ID": "6510902"},{"Date": "09/21/2008 02:40:00 PM", "Beat": "0821", "Primary Type": "STALKING", "ID": "6512504"},{"Date": "09/17/2008 09:30:00 AM", "Beat": "0312", "Primary Type": "STALKING", "ID": "6518445"},{"Date": "09/24/2008 11:00:00 AM", "Beat": "2535", "Primary Type": "STALKING", "ID": "6519408"},{"Date": "09/25/2008 11:31:51 PM", "Beat": "0711", "Primary Type": "STALKING", "ID": "6520090"},{"Date": "09/26/2008 04:20:38 PM", "Beat": "1033", "Primary Type": "STALKING", "ID": "6525603"},{"Date": "09/29/2008 11:45:00 AM", "Beat": "1731", "Primary Type": "STALKING", "ID": "6526800"},{"Date": "09/10/2008 12:00:00 PM", "Beat": "2535", "Primary Type": "STALKING", "ID": "6540464"},{"Date": "09/01/2008 09:00:00 AM", "Beat": "1033", "Primary Type": "STALKING", "ID": "6597457"},{"Date": "09/03/2008 11:24:00 AM", "Beat": "1124", "Primary Type": "STALKING", "ID": "6663675"},{"Date": "09/05/2008 07:00:00 AM", "Beat": "0331", "Primary Type": "STALKING", "ID": "6863158"}]